{
	"animations": [
		{
			"loop": true,
			"offsets": [
				-179,
				50
			],
			"anim": "idle",
			"fps": 24,
			"name": "Deimos Idle",
			"indices": []
		},
		{
			"loop": true,
			"offsets": [
				180,
				63
			],
			"anim": "singLEFT",
			"fps": 24,
			"name": "Deimos Left",
			"indices": []
		},
		{
			"loop": true,
			"offsets": [
				-70,
				-2
			],
			"anim": "singDOWN",
			"fps": 24,
			"name": "Deimos Down",
			"indices": []
		},
		{
			"loop": true,
			"offsets": [
				26,
				270
			],
			"anim": "singUP",
			"fps": 24,
			"name": "Deimos Up",
			"indices": []
		},
		{
			"loop": true,
			"offsets": [
				-120,
				100
			],
			"anim": "singRIGHT",
			"fps": 24,
			"name": "Deimos Right",
			"indices": []
		}
	],
	"no_antialiasing": false,
	"image": "characters/Deimos_Assets",
	"position": [
		0,
		0
	],
	"healthicon": "deimos",
	"flip_x": false,
	"healthbar_colors": [
		255,
		121,
		60
	],
	"camera_position": [
		0,
		0
	],
	"sing_duration": 6.1,
	"scale": 1
}