<?xml version="1.0" encoding="utf-8"?>
<TextureAtlas imagePath="Murderfucker_Death.png">
	<!-- Created with Adobe Animate version 21.0.6.41649 -->
	<!-- http://www.adobe.com/products/animate.html -->
	<SubTexture name="Hank Death0000" x="0" y="0" width="781" height="654" frameX="-40" frameY="-64" frameWidth="821" frameHeight="875"/>
	<SubTexture name="Hank Death0001" x="781" y="0" width="781" height="654" frameX="-40" frameY="-64" frameWidth="821" frameHeight="875"/>
	<SubTexture name="Hank Death0002" x="1562" y="0" width="761" height="654" frameX="-40" frameY="-64" frameWidth="821" frameHeight="875"/>
	<SubTexture name="Hank Death0003" x="2323" y="0" width="761" height="654" frameX="-40" frameY="-64" frameWidth="821" frameHeight="875"/>
	<SubTexture name="Hank Death0004" x="2323" y="0" width="761" height="654" frameX="-40" frameY="-64" frameWidth="821" frameHeight="875"/>
	<SubTexture name="Hank Death0005" x="3084" y="0" width="761" height="654" frameX="-40" frameY="-64" frameWidth="821" frameHeight="875"/>
	<SubTexture name="Hank Death0006" x="3845" y="0" width="761" height="654" frameX="-40" frameY="-64" frameWidth="821" frameHeight="875"/>
	<SubTexture name="Hank Death0007" x="3845" y="0" width="761" height="654" frameX="-40" frameY="-64" frameWidth="821" frameHeight="875"/>
	<SubTexture name="Hank Death0008" x="3845" y="0" width="761" height="654" frameX="-40" frameY="-64" frameWidth="821" frameHeight="875"/>
	<SubTexture name="Hank Death0009" x="3845" y="0" width="761" height="654" frameX="-40" frameY="-64" frameWidth="821" frameHeight="875"/>
	<SubTexture name="Hank Death0010" x="3845" y="0" width="761" height="654" frameX="-40" frameY="-64" frameWidth="821" frameHeight="875"/>
	<SubTexture name="Hank Death0011" x="3845" y="0" width="761" height="654" frameX="-40" frameY="-64" frameWidth="821" frameHeight="875"/>
	<SubTexture name="Hank Death0012" x="3845" y="0" width="761" height="654" frameX="-40" frameY="-64" frameWidth="821" frameHeight="875"/>
	<SubTexture name="Hank Death0013" x="3845" y="0" width="761" height="654" frameX="-40" frameY="-64" frameWidth="821" frameHeight="875"/>
	<SubTexture name="Hank Death0014" x="3845" y="0" width="761" height="654" frameX="-40" frameY="-64" frameWidth="821" frameHeight="875"/>
	<SubTexture name="Hank Death0015" x="4606" y="0" width="761" height="654" frameX="-40" frameY="-64" frameWidth="821" frameHeight="875"/>
	<SubTexture name="Hank Death0016" x="4606" y="0" width="761" height="654" frameX="-40" frameY="-64" frameWidth="821" frameHeight="875"/>
	<SubTexture name="Hank Death0017" x="4606" y="0" width="761" height="654" frameX="-40" frameY="-64" frameWidth="821" frameHeight="875"/>
	<SubTexture name="Hank Death0018" x="5367" y="0" width="761" height="654" frameX="-40" frameY="-64" frameWidth="821" frameHeight="875"/>
	<SubTexture name="Hank Death0019" x="5367" y="0" width="761" height="654" frameX="-40" frameY="-64" frameWidth="821" frameHeight="875"/>
	<SubTexture name="Hank Death0020" x="6128" y="0" width="761" height="654" frameX="-40" frameY="-64" frameWidth="821" frameHeight="875"/>
	<SubTexture name="Hank Death0021" x="6128" y="0" width="761" height="654" frameX="-40" frameY="-64" frameWidth="821" frameHeight="875"/>
	<SubTexture name="Hank Death0022" x="6889" y="0" width="761" height="654" frameX="-40" frameY="-64" frameWidth="821" frameHeight="875"/>
	<SubTexture name="Hank Death0023" x="6889" y="0" width="761" height="654" frameX="-40" frameY="-64" frameWidth="821" frameHeight="875"/>
	<SubTexture name="Hank Death0024" x="0" y="654" width="761" height="654" frameX="-40" frameY="-64" frameWidth="821" frameHeight="875"/>
	<SubTexture name="Hank Death0025" x="761" y="654" width="761" height="726" frameX="-40" frameY="-64" frameWidth="821" frameHeight="875"/>
	<SubTexture name="Hank Death0026" x="1522" y="654" width="761" height="772" frameX="-40" frameY="-64" frameWidth="821" frameHeight="875"/>
	<SubTexture name="Hank Death0027" x="2283" y="654" width="801" height="811" frameX="0" frameY="-64" frameWidth="821" frameHeight="875"/>
	<SubTexture name="Hank Death0028" x="3084" y="654" width="761" height="692" frameX="-40" frameY="-64" frameWidth="821" frameHeight="875"/>
	<SubTexture name="Hank Death0029" x="3845" y="654" width="761" height="692" frameX="-40" frameY="-64" frameWidth="821" frameHeight="875"/>
	<SubTexture name="Hank Death0030" x="3845" y="654" width="761" height="692" frameX="-40" frameY="-64" frameWidth="821" frameHeight="875"/>
	<SubTexture name="Hank Death0031" x="3845" y="654" width="761" height="692" frameX="-40" frameY="-64" frameWidth="821" frameHeight="875"/>
	<SubTexture name="Hank Death0032" x="3845" y="654" width="761" height="692" frameX="-40" frameY="-64" frameWidth="821" frameHeight="875"/>
	<SubTexture name="Hank Death0033" x="3845" y="654" width="761" height="692" frameX="-40" frameY="-64" frameWidth="821" frameHeight="875"/>
	<SubTexture name="Hank Death0034" x="2283" y="4505" width="761" height="730" frameX="-40" frameY="-15" frameWidth="761" frameHeight="774"/>
	<SubTexture name="Hank Death0035" x="4606" y="654" width="761" height="742" frameX="-40" frameY="-14" frameWidth="821" frameHeight="875"/>
	<SubTexture name="Hank Death0036" x="761" y="4505" width="761" height="744" frameX="-40" frameY="-14" frameWidth="761" frameHeight="774"/>
	<SubTexture name="Hank Death0037" x="5367" y="654" width="761" height="743" frameX="-40" frameY="-13" frameWidth="821" frameHeight="875"/>
	<SubTexture name="Hank Death0038" x="6128" y="654" width="761" height="744" frameX="-40" frameY="-12" frameWidth="821" frameHeight="875"/>
	<SubTexture name="Hank Death0039" x="6889" y="654" width="761" height="744" frameX="-40" frameY="-12" frameWidth="821" frameHeight="875"/>
	<SubTexture name="Hank Death0040" x="0" y="1465" width="761" height="745" frameX="-40" frameY="-11" frameWidth="821" frameHeight="875"/>
	<SubTexture name="Hank Death0041" x="761" y="1465" width="761" height="746" frameX="-40" frameY="-10" frameWidth="821" frameHeight="875"/>
	<SubTexture name="Hank Death0042" x="1522" y="1465" width="761" height="746" frameX="-40" frameY="-10" frameWidth="821" frameHeight="875"/>
	<SubTexture name="Hank Death0043" x="2283" y="1465" width="761" height="747" frameX="-40" frameY="-9" frameWidth="821" frameHeight="875"/>
	<SubTexture name="Hank Death0044" x="3044" y="1465" width="761" height="748" frameX="-40" frameY="-8" frameWidth="821" frameHeight="875"/>
	<SubTexture name="Hank Death0045" x="3805" y="1465" width="761" height="748" frameX="-40" frameY="-8" frameWidth="821" frameHeight="875"/>
	<SubTexture name="Hank Death0046" x="4566" y="1465" width="761" height="749" frameX="-40" frameY="-7" frameWidth="821" frameHeight="875"/>
	<SubTexture name="Hank Death0047" x="5327" y="1465" width="761" height="750" frameX="-40" frameY="-6" frameWidth="821" frameHeight="875"/>
	<SubTexture name="Hank Death0048" x="6088" y="1465" width="761" height="750" frameX="-40" frameY="-6" frameWidth="821" frameHeight="875"/>
	<SubTexture name="Hank Death0049" x="6849" y="1465" width="761" height="751" frameX="-40" frameY="-5" frameWidth="821" frameHeight="875"/>
	<SubTexture name="Hank Death0050" x="0" y="2216" width="761" height="752" frameX="-40" frameY="-4" frameWidth="821" frameHeight="875"/>
	<SubTexture name="Hank Death0051" x="761" y="2216" width="761" height="752" frameX="-40" frameY="-4" frameWidth="821" frameHeight="875"/>
	<SubTexture name="Hank Death0052" x="1522" y="2216" width="761" height="753" frameX="-40" frameY="-3" frameWidth="821" frameHeight="875"/>
	<SubTexture name="Hank Death0053" x="2283" y="2216" width="761" height="754" frameX="-40" frameY="-2" frameWidth="821" frameHeight="875"/>
	<SubTexture name="Hank Death0054" x="3044" y="2216" width="761" height="754" frameX="-40" frameY="-2" frameWidth="821" frameHeight="875"/>
	<SubTexture name="Hank Death0055" x="3805" y="2216" width="761" height="755" frameX="-40" frameY="-1" frameWidth="821" frameHeight="875"/>
	<SubTexture name="Hank Death0056" x="4566" y="2216" width="761" height="756" frameX="-40" frameY="0" frameWidth="821" frameHeight="875"/>
	<SubTexture name="Hank Death0057" x="4566" y="6010" width="761" height="730" frameX="-40" frameY="-26" frameWidth="761" frameHeight="756"/>
	<SubTexture name="Hank DeathConfirm0000" x="5327" y="2216" width="761" height="729" frameX="0" frameY="-45" frameWidth="761" frameHeight="774"/>
	<SubTexture name="Hank DeathConfirm0001" x="6088" y="2216" width="761" height="731" frameX="0" frameY="-43" frameWidth="761" frameHeight="774"/>
	<SubTexture name="Hank DeathConfirm0002" x="6849" y="2216" width="761" height="731" frameX="0" frameY="-43" frameWidth="761" frameHeight="774"/>
	<SubTexture name="Hank DeathConfirm0003" x="0" y="2972" width="761" height="774"/>
	<SubTexture name="Hank DeathConfirm0004" x="761" y="2972" width="761" height="772" frameX="0" frameY="-2" frameWidth="761" frameHeight="774"/>
	<SubTexture name="Hank DeathConfirm0005" x="1522" y="2972" width="761" height="771" frameX="0" frameY="-3" frameWidth="761" frameHeight="774"/>
	<SubTexture name="Hank DeathConfirm0006" x="2283" y="2972" width="761" height="769" frameX="0" frameY="-5" frameWidth="761" frameHeight="774"/>
	<SubTexture name="Hank DeathConfirm0007" x="3044" y="2972" width="761" height="768" frameX="0" frameY="-6" frameWidth="761" frameHeight="774"/>
	<SubTexture name="Hank DeathConfirm0008" x="3805" y="2972" width="761" height="766" frameX="0" frameY="-8" frameWidth="761" frameHeight="774"/>
	<SubTexture name="Hank DeathConfirm0009" x="4566" y="2972" width="761" height="765" frameX="0" frameY="-9" frameWidth="761" frameHeight="774"/>
	<SubTexture name="Hank DeathConfirm0010" x="5327" y="2972" width="761" height="764" frameX="0" frameY="-10" frameWidth="761" frameHeight="774"/>
	<SubTexture name="Hank DeathConfirm0011" x="6088" y="2972" width="761" height="762" frameX="0" frameY="-12" frameWidth="761" frameHeight="774"/>
	<SubTexture name="Hank DeathConfirm0012" x="6849" y="2972" width="761" height="761" frameX="0" frameY="-13" frameWidth="761" frameHeight="774"/>
	<SubTexture name="Hank DeathConfirm0013" x="0" y="3746" width="761" height="759" frameX="0" frameY="-15" frameWidth="761" frameHeight="774"/>
	<SubTexture name="Hank DeathConfirm0014" x="761" y="3746" width="761" height="758" frameX="0" frameY="-16" frameWidth="761" frameHeight="774"/>
	<SubTexture name="Hank DeathConfirm0015" x="1522" y="3746" width="761" height="757" frameX="0" frameY="-17" frameWidth="761" frameHeight="774"/>
	<SubTexture name="Hank DeathConfirm0016" x="2283" y="3746" width="761" height="755" frameX="0" frameY="-19" frameWidth="761" frameHeight="774"/>
	<SubTexture name="Hank DeathConfirm0017" x="3044" y="3746" width="761" height="754" frameX="0" frameY="-20" frameWidth="761" frameHeight="774"/>
	<SubTexture name="Hank DeathConfirm0018" x="3805" y="3746" width="761" height="752" frameX="0" frameY="-22" frameWidth="761" frameHeight="774"/>
	<SubTexture name="Hank DeathConfirm0019" x="4566" y="3746" width="761" height="751" frameX="0" frameY="-23" frameWidth="761" frameHeight="774"/>
	<SubTexture name="Hank DeathConfirm0020" x="5327" y="3746" width="761" height="749" frameX="0" frameY="-25" frameWidth="761" frameHeight="774"/>
	<SubTexture name="Hank DeathConfirm0021" x="6088" y="3746" width="761" height="748" frameX="0" frameY="-26" frameWidth="761" frameHeight="774"/>
	<SubTexture name="Hank DeathConfirm0022" x="6849" y="3746" width="761" height="747" frameX="0" frameY="-27" frameWidth="761" frameHeight="774"/>
	<SubTexture name="Hank DeathConfirm0023" x="0" y="4505" width="761" height="745" frameX="0" frameY="-29" frameWidth="761" frameHeight="774"/>
	<SubTexture name="Hank DeathConfirm0024" x="761" y="4505" width="761" height="744" frameX="0" frameY="-30" frameWidth="761" frameHeight="774"/>
	<SubTexture name="Hank DeathConfirm0025" x="1522" y="4505" width="761" height="742" frameX="0" frameY="-32" frameWidth="761" frameHeight="774"/>
	<SubTexture name="Hank DeathConfirm0026" x="2283" y="4505" width="761" height="730" frameX="0" frameY="-44" frameWidth="761" frameHeight="774"/>
	<SubTexture name="Hank DeathConfirm0027" x="2283" y="4505" width="761" height="730" frameX="0" frameY="-44" frameWidth="761" frameHeight="774"/>
	<SubTexture name="Hank DeathConfirm0028" x="2283" y="4505" width="761" height="730" frameX="0" frameY="-44" frameWidth="761" frameHeight="774"/>
	<SubTexture name="Hank DeathConfirm0029" x="2283" y="4505" width="761" height="730" frameX="0" frameY="-44" frameWidth="761" frameHeight="774"/>
	<SubTexture name="Hank DeathConfirm0030" x="2283" y="4505" width="761" height="730" frameX="0" frameY="-44" frameWidth="761" frameHeight="774"/>
	<SubTexture name="Hank DeathConfirm0031" x="2283" y="4505" width="761" height="730" frameX="0" frameY="-44" frameWidth="761" frameHeight="774"/>
	<SubTexture name="Hank DeathConfirm0032" x="2283" y="4505" width="761" height="730" frameX="0" frameY="-44" frameWidth="761" frameHeight="774"/>
	<SubTexture name="Hank DeathConfirm0033" x="2283" y="4505" width="761" height="730" frameX="0" frameY="-44" frameWidth="761" frameHeight="774"/>
	<SubTexture name="Hank DeathConfirm0034" x="2283" y="4505" width="761" height="730" frameX="0" frameY="-44" frameWidth="761" frameHeight="774"/>
	<SubTexture name="Hank DeathLoop0000" x="3044" y="4505" width="761" height="756"/>
	<SubTexture name="Hank DeathLoop0001" x="3805" y="4505" width="761" height="755" frameX="0" frameY="-1" frameWidth="761" frameHeight="756"/>
	<SubTexture name="Hank DeathLoop0002" x="4566" y="4505" width="761" height="754" frameX="0" frameY="-2" frameWidth="761" frameHeight="756"/>
	<SubTexture name="Hank DeathLoop0003" x="5327" y="4505" width="761" height="753" frameX="0" frameY="-3" frameWidth="761" frameHeight="756"/>
	<SubTexture name="Hank DeathLoop0004" x="6088" y="4505" width="761" height="751" frameX="0" frameY="-5" frameWidth="761" frameHeight="756"/>
	<SubTexture name="Hank DeathLoop0005" x="6849" y="4505" width="761" height="750" frameX="0" frameY="-6" frameWidth="761" frameHeight="756"/>
	<SubTexture name="Hank DeathLoop0006" x="0" y="5261" width="761" height="749" frameX="0" frameY="-7" frameWidth="761" frameHeight="756"/>
	<SubTexture name="Hank DeathLoop0007" x="761" y="5261" width="761" height="748" frameX="0" frameY="-8" frameWidth="761" frameHeight="756"/>
	<SubTexture name="Hank DeathLoop0008" x="1522" y="5261" width="761" height="746" frameX="0" frameY="-10" frameWidth="761" frameHeight="756"/>
	<SubTexture name="Hank DeathLoop0009" x="2283" y="5261" width="761" height="745" frameX="0" frameY="-11" frameWidth="761" frameHeight="756"/>
	<SubTexture name="Hank DeathLoop0010" x="3044" y="5261" width="761" height="744" frameX="0" frameY="-12" frameWidth="761" frameHeight="756"/>
	<SubTexture name="Hank DeathLoop0011" x="3805" y="5261" width="761" height="743" frameX="0" frameY="-13" frameWidth="761" frameHeight="756"/>
	<SubTexture name="Hank DeathLoop0012" x="4566" y="5261" width="761" height="741" frameX="0" frameY="-15" frameWidth="761" frameHeight="756"/>
	<SubTexture name="Hank DeathLoop0013" x="5327" y="5261" width="761" height="740" frameX="0" frameY="-16" frameWidth="761" frameHeight="756"/>
	<SubTexture name="Hank DeathLoop0014" x="6088" y="5261" width="761" height="739" frameX="0" frameY="-17" frameWidth="761" frameHeight="756"/>
	<SubTexture name="Hank DeathLoop0015" x="6849" y="5261" width="761" height="738" frameX="0" frameY="-18" frameWidth="761" frameHeight="756"/>
	<SubTexture name="Hank DeathLoop0016" x="0" y="6010" width="761" height="736" frameX="0" frameY="-20" frameWidth="761" frameHeight="756"/>
	<SubTexture name="Hank DeathLoop0017" x="761" y="6010" width="761" height="735" frameX="0" frameY="-21" frameWidth="761" frameHeight="756"/>
	<SubTexture name="Hank DeathLoop0018" x="0" y="6010" width="761" height="736" frameX="0" frameY="-20" frameWidth="761" frameHeight="756"/>
	<SubTexture name="Hank DeathLoop0019" x="6849" y="5261" width="761" height="738" frameX="0" frameY="-18" frameWidth="761" frameHeight="756"/>
	<SubTexture name="Hank DeathLoop0020" x="1522" y="6010" width="761" height="739" frameX="0" frameY="-17" frameWidth="761" frameHeight="756"/>
	<SubTexture name="Hank DeathLoop0021" x="2283" y="6010" width="761" height="740" frameX="0" frameY="-16" frameWidth="761" frameHeight="756"/>
	<SubTexture name="Hank DeathLoop0022" x="4566" y="5261" width="761" height="741" frameX="0" frameY="-14" frameWidth="761" frameHeight="756"/>
	<SubTexture name="Hank DeathLoop0023" x="3805" y="5261" width="761" height="743" frameX="0" frameY="-13" frameWidth="761" frameHeight="756"/>
	<SubTexture name="Hank DeathLoop0024" x="2283" y="5261" width="761" height="745" frameX="0" frameY="-12" frameWidth="761" frameHeight="756"/>
	<SubTexture name="Hank DeathLoop0025" x="3044" y="6010" width="761" height="746" frameX="0" frameY="-10" frameWidth="761" frameHeight="756"/>
	<SubTexture name="Hank DeathLoop0026" x="1522" y="5261" width="761" height="746" frameX="0" frameY="-9" frameWidth="761" frameHeight="756"/>
	<SubTexture name="Hank DeathLoop0027" x="761" y="5261" width="761" height="748" frameX="0" frameY="-8" frameWidth="761" frameHeight="756"/>
	<SubTexture name="Hank DeathLoop0028" x="6849" y="4505" width="761" height="750" frameX="0" frameY="-6" frameWidth="761" frameHeight="756"/>
	<SubTexture name="Hank DeathLoop0029" x="6088" y="4505" width="761" height="751" frameX="0" frameY="-5" frameWidth="761" frameHeight="756"/>
	<SubTexture name="Hank DeathLoop0030" x="3805" y="6010" width="761" height="752" frameX="0" frameY="-4" frameWidth="761" frameHeight="756"/>
	<SubTexture name="Hank DeathLoop0031" x="4566" y="4505" width="761" height="754" frameX="0" frameY="-2" frameWidth="761" frameHeight="756"/>
	<SubTexture name="Hank DeathLoop0032" x="3805" y="4505" width="761" height="755" frameX="0" frameY="-1" frameWidth="761" frameHeight="756"/>
	<SubTexture name="Hank DeathLoop0033" x="4566" y="6010" width="761" height="730" frameX="0" frameY="-26" frameWidth="761" frameHeight="756"/>
</TextureAtlas>
