<?xml version="1.0" encoding="utf-8"?>
<TextureAtlas imagePath="Murderfucker_Death.png">
	<!-- Created with Adobe Animate version 21.0.6.41649 -->
	<!-- http://www.adobe.com/products/animate.html -->
	<SubTexture name="Hank Death 0000" x="0" y="0" width="782" height="655" frameX="-39" frameY="-65" frameWidth="821" frameHeight="876"/>
	<SubTexture name="Hank Death 0001" x="782" y="0" width="782" height="655" frameX="-39" frameY="-65" frameWidth="821" frameHeight="876"/>
	<SubTexture name="Hank Death 0002" x="1564" y="0" width="762" height="655" frameX="-39" frameY="-65" frameWidth="821" frameHeight="876"/>
	<SubTexture name="Hank Death 0003" x="2326" y="0" width="762" height="655" frameX="-39" frameY="-65" frameWidth="821" frameHeight="876"/>
	<SubTexture name="Hank Death 0004" x="2326" y="0" width="762" height="655" frameX="-39" frameY="-65" frameWidth="821" frameHeight="876"/>
	<SubTexture name="Hank Death 0005" x="3088" y="0" width="762" height="655" frameX="-39" frameY="-65" frameWidth="821" frameHeight="876"/>
	<SubTexture name="Hank Death 0006" x="3850" y="0" width="762" height="655" frameX="-39" frameY="-65" frameWidth="821" frameHeight="876"/>
	<SubTexture name="Hank Death 0007" x="3850" y="0" width="762" height="655" frameX="-39" frameY="-65" frameWidth="821" frameHeight="876"/>
	<SubTexture name="Hank Death 0008" x="3850" y="0" width="762" height="655" frameX="-39" frameY="-65" frameWidth="821" frameHeight="876"/>
	<SubTexture name="Hank Death 0009" x="3850" y="0" width="762" height="655" frameX="-39" frameY="-65" frameWidth="821" frameHeight="876"/>
	<SubTexture name="Hank Death 0010" x="3850" y="0" width="762" height="655" frameX="-39" frameY="-65" frameWidth="821" frameHeight="876"/>
	<SubTexture name="Hank Death 0011" x="3850" y="0" width="762" height="655" frameX="-39" frameY="-65" frameWidth="821" frameHeight="876"/>
	<SubTexture name="Hank Death 0012" x="3850" y="0" width="762" height="655" frameX="-39" frameY="-65" frameWidth="821" frameHeight="876"/>
	<SubTexture name="Hank Death 0013" x="3850" y="0" width="762" height="655" frameX="-39" frameY="-65" frameWidth="821" frameHeight="876"/>
	<SubTexture name="Hank Death 0014" x="3850" y="0" width="762" height="655" frameX="-39" frameY="-65" frameWidth="821" frameHeight="876"/>
	<SubTexture name="Hank Death 0015" x="4612" y="0" width="762" height="655" frameX="-39" frameY="-65" frameWidth="821" frameHeight="876"/>
	<SubTexture name="Hank Death 0016" x="4612" y="0" width="762" height="655" frameX="-39" frameY="-65" frameWidth="821" frameHeight="876"/>
	<SubTexture name="Hank Death 0017" x="4612" y="0" width="762" height="655" frameX="-39" frameY="-65" frameWidth="821" frameHeight="876"/>
	<SubTexture name="Hank Death 0018" x="5374" y="0" width="762" height="655" frameX="-39" frameY="-65" frameWidth="821" frameHeight="876"/>
	<SubTexture name="Hank Death 0019" x="5374" y="0" width="762" height="655" frameX="-39" frameY="-65" frameWidth="821" frameHeight="876"/>
	<SubTexture name="Hank Death 0020" x="6136" y="0" width="762" height="655" frameX="-39" frameY="-65" frameWidth="821" frameHeight="876"/>
	<SubTexture name="Hank Death 0021" x="6136" y="0" width="762" height="655" frameX="-39" frameY="-65" frameWidth="821" frameHeight="876"/>
	<SubTexture name="Hank Death 0022" x="6898" y="0" width="762" height="655" frameX="-39" frameY="-65" frameWidth="821" frameHeight="876"/>
	<SubTexture name="Hank Death 0023" x="6898" y="0" width="762" height="655" frameX="-39" frameY="-65" frameWidth="821" frameHeight="876"/>
	<SubTexture name="Hank Death 0024" x="0" y="655" width="762" height="655" frameX="-39" frameY="-65" frameWidth="821" frameHeight="876"/>
	<SubTexture name="Hank Death 0025" x="762" y="655" width="762" height="726" frameX="-39" frameY="-65" frameWidth="821" frameHeight="876"/>
	<SubTexture name="Hank Death 0026" x="1524" y="655" width="762" height="772" frameX="-39" frameY="-65" frameWidth="821" frameHeight="876"/>
	<SubTexture name="Hank Death 0027" x="2286" y="655" width="801" height="811" frameX="0" frameY="-65" frameWidth="821" frameHeight="876"/>
	<SubTexture name="Hank Death 0028" x="3087" y="655" width="762" height="693" frameX="-39" frameY="-65" frameWidth="821" frameHeight="876"/>
	<SubTexture name="Hank Death 0029" x="3849" y="655" width="762" height="693" frameX="-39" frameY="-65" frameWidth="821" frameHeight="876"/>
	<SubTexture name="Hank Death 0030" x="3849" y="655" width="762" height="693" frameX="-39" frameY="-65" frameWidth="821" frameHeight="876"/>
	<SubTexture name="Hank Death 0031" x="3849" y="655" width="762" height="693" frameX="-39" frameY="-65" frameWidth="821" frameHeight="876"/>
	<SubTexture name="Hank Death 0032" x="3849" y="655" width="762" height="693" frameX="-39" frameY="-65" frameWidth="821" frameHeight="876"/>
	<SubTexture name="Hank Death 0033" x="3849" y="655" width="762" height="693" frameX="-39" frameY="-65" frameWidth="821" frameHeight="876"/>
	<SubTexture name="Hank Death 0034" x="4611" y="655" width="762" height="743" frameX="-39" frameY="-15" frameWidth="821" frameHeight="876"/>
	<SubTexture name="Hank Death 0035" x="5373" y="655" width="762" height="744" frameX="-39" frameY="-14" frameWidth="821" frameHeight="876"/>
	<SubTexture name="Hank Death 0036" x="6135" y="655" width="762" height="744" frameX="-39" frameY="-14" frameWidth="821" frameHeight="876"/>
	<SubTexture name="Hank Death 0037" x="6897" y="655" width="762" height="745" frameX="-39" frameY="-13" frameWidth="821" frameHeight="876"/>
	<SubTexture name="Hank Death 0038" x="0" y="1466" width="762" height="746" frameX="-39" frameY="-12" frameWidth="821" frameHeight="876"/>
	<SubTexture name="Hank Death 0039" x="762" y="1466" width="762" height="746" frameX="-39" frameY="-12" frameWidth="821" frameHeight="876"/>
	<SubTexture name="Hank Death 0040" x="1524" y="1466" width="762" height="747" frameX="-39" frameY="-11" frameWidth="821" frameHeight="876"/>
	<SubTexture name="Hank Death 0041" x="2286" y="1466" width="762" height="748" frameX="-39" frameY="-10" frameWidth="821" frameHeight="876"/>
	<SubTexture name="Hank Death 0042" x="3048" y="1466" width="762" height="748" frameX="-39" frameY="-10" frameWidth="821" frameHeight="876"/>
	<SubTexture name="Hank Death 0043" x="3810" y="1466" width="762" height="749" frameX="-39" frameY="-9" frameWidth="821" frameHeight="876"/>
	<SubTexture name="Hank Death 0044" x="4572" y="1466" width="762" height="750" frameX="-39" frameY="-8" frameWidth="821" frameHeight="876"/>
	<SubTexture name="Hank Death 0045" x="5334" y="1466" width="762" height="750" frameX="-39" frameY="-8" frameWidth="821" frameHeight="876"/>
	<SubTexture name="Hank Death 0046" x="6096" y="1466" width="762" height="751" frameX="-39" frameY="-7" frameWidth="821" frameHeight="876"/>
	<SubTexture name="Hank Death 0047" x="6858" y="1466" width="762" height="752" frameX="-39" frameY="-6" frameWidth="821" frameHeight="876"/>
	<SubTexture name="Hank Death 0048" x="0" y="2218" width="762" height="752" frameX="-39" frameY="-6" frameWidth="821" frameHeight="876"/>
	<SubTexture name="Hank Death 0049" x="762" y="2218" width="762" height="753" frameX="-39" frameY="-5" frameWidth="821" frameHeight="876"/>
	<SubTexture name="Hank Death 0050" x="1524" y="2218" width="762" height="754" frameX="-39" frameY="-4" frameWidth="821" frameHeight="876"/>
	<SubTexture name="Hank Death 0051" x="2286" y="2218" width="762" height="754" frameX="-39" frameY="-4" frameWidth="821" frameHeight="876"/>
	<SubTexture name="Hank Death 0052" x="3048" y="2218" width="762" height="755" frameX="-39" frameY="-3" frameWidth="821" frameHeight="876"/>
	<SubTexture name="Hank Death 0053" x="3810" y="2218" width="762" height="756" frameX="-39" frameY="-2" frameWidth="821" frameHeight="876"/>
	<SubTexture name="Hank Death 0054" x="4572" y="2218" width="762" height="756" frameX="-39" frameY="-2" frameWidth="821" frameHeight="876"/>
	<SubTexture name="Hank Death 0055" x="5334" y="2218" width="762" height="757" frameX="-39" frameY="-1" frameWidth="821" frameHeight="876"/>
	<SubTexture name="Hank Death 0056" x="6096" y="2218" width="762" height="758" frameX="-39" frameY="0" frameWidth="821" frameHeight="876"/>
	<SubTexture name="Hank Death 0057" x="6858" y="2218" width="762" height="732" frameX="-39" frameY="-26" frameWidth="821" frameHeight="876"/>
	<SubTexture name="Hank DeathConfirm0000" x="0" y="2976" width="761" height="729" frameX="0" frameY="-45" frameWidth="761" frameHeight="774"/>
	<SubTexture name="Hank DeathConfirm0001" x="761" y="2976" width="761" height="731" frameX="0" frameY="-43" frameWidth="761" frameHeight="774"/>
	<SubTexture name="Hank DeathConfirm0002" x="1522" y="2976" width="761" height="731" frameX="0" frameY="-43" frameWidth="761" frameHeight="774"/>
	<SubTexture name="Hank DeathConfirm0003" x="2283" y="2976" width="761" height="774"/>
	<SubTexture name="Hank DeathConfirm0004" x="3044" y="2976" width="761" height="772" frameX="0" frameY="-2" frameWidth="761" frameHeight="774"/>
	<SubTexture name="Hank DeathConfirm0005" x="3805" y="2976" width="761" height="771" frameX="0" frameY="-3" frameWidth="761" frameHeight="774"/>
	<SubTexture name="Hank DeathConfirm0006" x="4566" y="2976" width="761" height="769" frameX="0" frameY="-5" frameWidth="761" frameHeight="774"/>
	<SubTexture name="Hank DeathConfirm0007" x="5327" y="2976" width="761" height="768" frameX="0" frameY="-6" frameWidth="761" frameHeight="774"/>
	<SubTexture name="Hank DeathConfirm0008" x="6088" y="2976" width="761" height="766" frameX="0" frameY="-8" frameWidth="761" frameHeight="774"/>
	<SubTexture name="Hank DeathConfirm0009" x="6849" y="2976" width="761" height="765" frameX="0" frameY="-9" frameWidth="761" frameHeight="774"/>
	<SubTexture name="Hank DeathConfirm0010" x="0" y="3750" width="761" height="764" frameX="0" frameY="-10" frameWidth="761" frameHeight="774"/>
	<SubTexture name="Hank DeathConfirm0011" x="761" y="3750" width="761" height="762" frameX="0" frameY="-12" frameWidth="761" frameHeight="774"/>
	<SubTexture name="Hank DeathConfirm0012" x="1522" y="3750" width="761" height="761" frameX="0" frameY="-13" frameWidth="761" frameHeight="774"/>
	<SubTexture name="Hank DeathConfirm0013" x="2283" y="3750" width="761" height="759" frameX="0" frameY="-15" frameWidth="761" frameHeight="774"/>
	<SubTexture name="Hank DeathConfirm0014" x="3044" y="3750" width="761" height="758" frameX="0" frameY="-16" frameWidth="761" frameHeight="774"/>
	<SubTexture name="Hank DeathConfirm0015" x="3805" y="3750" width="761" height="757" frameX="0" frameY="-17" frameWidth="761" frameHeight="774"/>
	<SubTexture name="Hank DeathConfirm0016" x="4566" y="3750" width="761" height="755" frameX="0" frameY="-19" frameWidth="761" frameHeight="774"/>
	<SubTexture name="Hank DeathConfirm0017" x="5327" y="3750" width="761" height="754" frameX="0" frameY="-20" frameWidth="761" frameHeight="774"/>
	<SubTexture name="Hank DeathConfirm0018" x="6088" y="3750" width="761" height="752" frameX="0" frameY="-22" frameWidth="761" frameHeight="774"/>
	<SubTexture name="Hank DeathConfirm0019" x="6849" y="3750" width="761" height="751" frameX="0" frameY="-23" frameWidth="761" frameHeight="774"/>
	<SubTexture name="Hank DeathConfirm0020" x="0" y="4514" width="761" height="749" frameX="0" frameY="-25" frameWidth="761" frameHeight="774"/>
	<SubTexture name="Hank DeathConfirm0021" x="761" y="4514" width="761" height="748" frameX="0" frameY="-26" frameWidth="761" frameHeight="774"/>
	<SubTexture name="Hank DeathConfirm0022" x="1522" y="4514" width="761" height="747" frameX="0" frameY="-27" frameWidth="761" frameHeight="774"/>
	<SubTexture name="Hank DeathConfirm0023" x="2283" y="4514" width="761" height="745" frameX="0" frameY="-29" frameWidth="761" frameHeight="774"/>
	<SubTexture name="Hank DeathConfirm0024" x="6135" y="655" width="762" height="744" frameX="0" frameY="-30" frameWidth="821" frameHeight="876"/>
	<SubTexture name="Hank DeathConfirm0025" x="3044" y="4514" width="761" height="742" frameX="0" frameY="-32" frameWidth="761" frameHeight="774"/>
	<SubTexture name="Hank DeathConfirm0026" x="3805" y="4514" width="761" height="730" frameX="0" frameY="-44" frameWidth="761" frameHeight="774"/>
	<SubTexture name="Hank DeathConfirm0027" x="3805" y="4514" width="761" height="730" frameX="0" frameY="-44" frameWidth="761" frameHeight="774"/>
	<SubTexture name="Hank DeathConfirm0028" x="3805" y="4514" width="761" height="730" frameX="0" frameY="-44" frameWidth="761" frameHeight="774"/>
	<SubTexture name="Hank DeathConfirm0029" x="3805" y="4514" width="761" height="730" frameX="0" frameY="-44" frameWidth="761" frameHeight="774"/>
	<SubTexture name="Hank DeathConfirm0030" x="3805" y="4514" width="761" height="730" frameX="0" frameY="-44" frameWidth="761" frameHeight="774"/>
	<SubTexture name="Hank DeathConfirm0031" x="3805" y="4514" width="761" height="730" frameX="0" frameY="-44" frameWidth="761" frameHeight="774"/>
	<SubTexture name="Hank DeathConfirm0032" x="3805" y="4514" width="761" height="730" frameX="0" frameY="-44" frameWidth="761" frameHeight="774"/>
	<SubTexture name="Hank DeathConfirm0033" x="3805" y="4514" width="761" height="730" frameX="0" frameY="-44" frameWidth="761" frameHeight="774"/>
	<SubTexture name="Hank DeathConfirm0034" x="3805" y="4514" width="761" height="730" frameX="0" frameY="-44" frameWidth="761" frameHeight="774"/>
	<SubTexture name="Hank DeathLoop0000" x="4566" y="4514" width="761" height="756"/>
	<SubTexture name="Hank DeathLoop0001" x="5327" y="4514" width="761" height="755" frameX="0" frameY="-1" frameWidth="761" frameHeight="756"/>
	<SubTexture name="Hank DeathLoop0002" x="6088" y="4514" width="761" height="754" frameX="0" frameY="-2" frameWidth="761" frameHeight="756"/>
	<SubTexture name="Hank DeathLoop0003" x="6849" y="4514" width="761" height="753" frameX="0" frameY="-3" frameWidth="761" frameHeight="756"/>
	<SubTexture name="Hank DeathLoop0004" x="0" y="5270" width="761" height="751" frameX="0" frameY="-5" frameWidth="761" frameHeight="756"/>
	<SubTexture name="Hank DeathLoop0005" x="761" y="5270" width="761" height="750" frameX="0" frameY="-6" frameWidth="761" frameHeight="756"/>
	<SubTexture name="Hank DeathLoop0006" x="1522" y="5270" width="761" height="749" frameX="0" frameY="-7" frameWidth="761" frameHeight="756"/>
	<SubTexture name="Hank DeathLoop0007" x="2283" y="5270" width="761" height="748" frameX="0" frameY="-8" frameWidth="761" frameHeight="756"/>
	<SubTexture name="Hank DeathLoop0008" x="3044" y="5270" width="761" height="746" frameX="0" frameY="-10" frameWidth="761" frameHeight="756"/>
	<SubTexture name="Hank DeathLoop0009" x="3805" y="5270" width="761" height="745" frameX="0" frameY="-11" frameWidth="761" frameHeight="756"/>
	<SubTexture name="Hank DeathLoop0010" x="4566" y="5270" width="761" height="744" frameX="0" frameY="-12" frameWidth="761" frameHeight="756"/>
	<SubTexture name="Hank DeathLoop0011" x="5327" y="5270" width="761" height="743" frameX="0" frameY="-13" frameWidth="761" frameHeight="756"/>
	<SubTexture name="Hank DeathLoop0012" x="6088" y="5270" width="761" height="741" frameX="0" frameY="-15" frameWidth="761" frameHeight="756"/>
	<SubTexture name="Hank DeathLoop0013" x="6849" y="5270" width="761" height="740" frameX="0" frameY="-16" frameWidth="761" frameHeight="756"/>
	<SubTexture name="Hank DeathLoop0014" x="0" y="6021" width="761" height="739" frameX="0" frameY="-17" frameWidth="761" frameHeight="756"/>
	<SubTexture name="Hank DeathLoop0015" x="761" y="6021" width="761" height="738" frameX="0" frameY="-18" frameWidth="761" frameHeight="756"/>
	<SubTexture name="Hank DeathLoop0016" x="1522" y="6021" width="761" height="736" frameX="0" frameY="-20" frameWidth="761" frameHeight="756"/>
	<SubTexture name="Hank DeathLoop0017" x="2283" y="6021" width="761" height="735" frameX="0" frameY="-21" frameWidth="761" frameHeight="756"/>
	<SubTexture name="Hank DeathLoop0018" x="1522" y="6021" width="761" height="736" frameX="0" frameY="-20" frameWidth="761" frameHeight="756"/>
	<SubTexture name="Hank DeathLoop0019" x="761" y="6021" width="761" height="738" frameX="0" frameY="-18" frameWidth="761" frameHeight="756"/>
	<SubTexture name="Hank DeathLoop0020" x="3044" y="6021" width="761" height="739" frameX="0" frameY="-17" frameWidth="761" frameHeight="756"/>
	<SubTexture name="Hank DeathLoop0021" x="3805" y="6021" width="761" height="740" frameX="0" frameY="-16" frameWidth="761" frameHeight="756"/>
	<SubTexture name="Hank DeathLoop0022" x="6088" y="5270" width="761" height="741" frameX="0" frameY="-14" frameWidth="761" frameHeight="756"/>
	<SubTexture name="Hank DeathLoop0023" x="5327" y="5270" width="761" height="743" frameX="0" frameY="-13" frameWidth="761" frameHeight="756"/>
	<SubTexture name="Hank DeathLoop0024" x="3805" y="5270" width="761" height="745" frameX="0" frameY="-12" frameWidth="761" frameHeight="756"/>
	<SubTexture name="Hank DeathLoop0025" x="4566" y="6021" width="761" height="746" frameX="0" frameY="-10" frameWidth="761" frameHeight="756"/>
	<SubTexture name="Hank DeathLoop0026" x="3044" y="5270" width="761" height="746" frameX="0" frameY="-9" frameWidth="761" frameHeight="756"/>
	<SubTexture name="Hank DeathLoop0027" x="2283" y="5270" width="761" height="748" frameX="0" frameY="-8" frameWidth="761" frameHeight="756"/>
	<SubTexture name="Hank DeathLoop0028" x="761" y="5270" width="761" height="750" frameX="0" frameY="-6" frameWidth="761" frameHeight="756"/>
	<SubTexture name="Hank DeathLoop0029" x="0" y="5270" width="761" height="751" frameX="0" frameY="-5" frameWidth="761" frameHeight="756"/>
	<SubTexture name="Hank DeathLoop0030" x="5327" y="6021" width="761" height="752" frameX="0" frameY="-4" frameWidth="761" frameHeight="756"/>
	<SubTexture name="Hank DeathLoop0031" x="6088" y="4514" width="761" height="754" frameX="0" frameY="-2" frameWidth="761" frameHeight="756"/>
	<SubTexture name="Hank DeathLoop0032" x="5327" y="4514" width="761" height="755" frameX="0" frameY="-1" frameWidth="761" frameHeight="756"/>
	<SubTexture name="Hank DeathLoop0033" x="6088" y="6021" width="761" height="730" frameX="0" frameY="-26" frameWidth="761" frameHeight="756"/>
</TextureAtlas>
